sirp_test/__init__.py
sirp_test/main.abi3.so
sirp_test-1.0.2.dist-info/licenses/LICENSE
sirp_test-1.0.2.dist-info/METADATA
sirp_test-1.0.2.dist-info/WHEEL
sirp_test-1.0.2.dist-info/top_level.txt
sirp_test-1.0.2.dist-info/RECORD
