Metadata-Version: 2.4
Name: sirp_test
Version: 1.0.2
Summary: A small test package
Author: Muhammad Waqar Anwar
Author-email: Muhammad Waqar Anwar <waqar@sirp.io>
License-Expression: MIT
Classifier: Programming Language :: Python :: 3
Classifier: Operating System :: POSIX :: Linux
Requires-Python: <3.14,>=3.10
License-File: LICENSE
Requires-Dist: requests>=2.32.5
Dynamic: author
Dynamic: license-file
